{
  "음식": {
    "normal": ["김치", "피자", "치킨", "초밥", "떡볶이", "불고기", "된장찌개", "삼겹살", "비빔밥", "잡채"],
    "fool": ["라면", "햄버거", "샐러드", "스파게티", "돈까스", "크림수프", "핫도그", "탕수육", "카레", "오므라이스"]
  },
  "동물": {
    "normal": ["고양이", "강아지", "호랑이", "코끼리", "토끼", "기린", "판다", "하마", "다람쥐", "앵무새"],
    "fool": ["여우", "늑대", "곰", "사자", "치타", "돌고래", "악어", "돼지", "오리", "늑대개"]
  },
  "장소": {
    "normal": ["학교", "공원", "도서관", "카페", "영화관", "버스정류장", "지하철역", "놀이터", "산책로", "교실"],
    "fool": ["식당", "병원", "마트", "은행", "미용실", "헬스장", "놀이공원", "기차역", "공항", "사진관"]
  },
  "영화": {
    "normal": ["기생충", "인셉션", "아바타", "겨울왕국", "해리포터", "인터스텔라", "코코", "주토피아", "엘리멘탈", "알라딘"],
    "fool": ["반지의 제왕", "매트릭스", "토이스토리", "어벤져스", "라라랜드", "아이언맨", "터미네이터", "트와일라잇", "덩케르크", "셜록"]
  },
  "직업": {
    "normal": ["의사", "간호사", "선생님", "경찰", "소방관", "요리사", "운동선수", "과학자", "배우", "개발자"],
    "fool": ["가수", "모델", "코미디언", "디자이너", "바리스타", "플로리스트", "건축가", "마술사", "감독", "스턴트맨"]
  },
  "스포츠": {
    "normal": ["축구", "야구", "농구", "배구", "탁구", "테니스", "수영", "볼링", "씨름", "족구"],
    "fool": ["럭비", "승마", "크리켓", "펜싱", "스쿼시", "컬링", "복싱", "양궁", "체조", "카약"]
  },
  "과일": {
    "normal": ["사과", "바나나", "포도", "딸기", "수박", "참외", "오렌지", "자두", "복숭아", "귤"],
    "fool": ["레몬", "라임", "파인애플", "블루베리", "망고", "체리", "키위", "석류", "용과", "두리안"]
  },
  "게임": {
    "normal": ["롤", "배그", "마인크래프트", "포켓몬스터", "젤다의 전설", "슈퍼마리오", "동물의숲", "하스스톤", "스타크래프트", "피파"],
    "fool": ["리니지", "메이플스토리", "서든어택", "오버워치", "사이퍼즈", "테일즈런너", "던전앤파이터", "포트나이트", "와우", "디아블로"]
  }
}
